branthebuilder/__init__.py
branthebuilder/main.py
branthebuilder/nb_scripts.py
branthebuilder/vars.py
branthebuilder/tests/test_integration.py
branthebuilder-1.0.12.dist-info/entry_points.txt
branthebuilder-1.0.12.dist-info/LICENSE
branthebuilder-1.0.12.dist-info/WHEEL
branthebuilder-1.0.12.dist-info/METADATA
branthebuilder-1.0.12.dist-info/RECORD
