Metadata-Version: 2.1
Name: branthebuilder
Version: 1.0.12
Summary: Python package management
Author-email: Endre Márk Borza <endremborza@gmail.com>
Requires-Python: >=3.8
Requires-Dist: typer
Requires-Dist: flit
Requires-Dist: jupyter
Requires-Dist: black
Requires-Dist: pytest
Requires-Dist: pytest-cov
Requires-Dist: toml
Requires-Dist: flake8
Requires-Dist: isort
Requires-Dist: cookiecutter
Requires-Dist: pyyaml
Requires-Dist: sphinx ; extra == "doc"
Requires-Dist: graphviz ; extra == "doc"
Requires-Dist: pandoc ; extra == "doc"
Requires-Dist: sphinx-automodapi ; extra == "doc"
Requires-Dist: sphinx-rtd-theme ; extra == "doc"
Requires-Dist: myst-parser ; extra == "doc"
Requires-Dist: pygments ; extra == "doc"
Project-URL: Homepage, https://github.com/endremborza/branthebuilder
Provides-Extra: doc
Provides-Extra: test
